django_blocklist/__init__.py
django_blocklist/admin.py
django_blocklist/apps.py
django_blocklist/management/__init__.py
django_blocklist/management/commands/__init__.py
django_blocklist/management/commands/clean_blocklist.py
django_blocklist/management/commands/fake_blocklist.py
django_blocklist/management/commands/import_blocklist.py
django_blocklist/management/commands/print_blocklist.py
django_blocklist/management/commands/remove_from_blocklist.py
django_blocklist/management/commands/report_blocklist.py
django_blocklist/management/commands/search_blocklist.py
django_blocklist/management/commands/update_blocklist.py
django_blocklist/middleware.py
django_blocklist/migrations/0001_initial.py
django_blocklist/migrations/0002_alter_blockedip_tally.py
django_blocklist/migrations/0003_rename_first_seen_to_datetime_added.py
django_blocklist/migrations/0004_alter_blockedip_options.py
django_blocklist/migrations/0005_blockedip_allowed_methods.py
django_blocklist/migrations/0006_blockedip_internal_notes.py
django_blocklist/migrations/__init__.py
django_blocklist/models.py
django_blocklist/py.typed
django_blocklist/tests/__init__.py
django_blocklist/tests/test_management.py
django_blocklist/tests/test_middleware.py
django_blocklist/tests/test_models.py
django_blocklist/tests/test_settings.py
django_blocklist/tests/test_utils.py
django_blocklist/utils.py
django_blocklist-3.2.1.dist-info/METADATA
django_blocklist-3.2.1.dist-info/WHEEL
django_blocklist-3.2.1.dist-info/licenses/LICENSE.md
django_blocklist-3.2.1.dist-info/RECORD
