Metadata-Version: 2.4
Name: django-blocklist
Version: 3.2.1
Summary: A Django app that implements IP-based blocklisting.
License-Expression: BSD-3-Clause
License-File: LICENSE.md
Author: Paul Bissex
Author-email: paul@bissex.net
Requires-Python: >=3.11,<4.0
Classifier: Programming Language :: Python :: 3
Classifier: Programming Language :: Python :: 3.11
Classifier: Programming Language :: Python :: 3.12
Classifier: Programming Language :: Python :: 3.13
Classifier: Programming Language :: Python :: 3.14
Provides-Extra: dev
Requires-Dist: Django (>=4.2,<7)
Requires-Dist: django-enum (>=2.3)
Requires-Dist: django-stubs[compatible-mypy] ; extra == "dev"
Requires-Dist: mypy ; extra == "dev"
Requires-Dist: poetry ; extra == "dev"
Requires-Dist: pytest ; extra == "dev"
Requires-Dist: pytest-django ; extra == "dev"
Requires-Dist: ruff ; extra == "dev"
Requires-Dist: tox ; extra == "dev"
Project-URL: Bug Tracker, https://gitlab.com/paul_bissex/django-blocklist/-/issues
Project-URL: Changelog, https://gitlab.com/paul_bissex/django-blocklist/-/blob/trunk/CHANGELOG.md
Project-URL: Documentation, https://gitlab.com/paul_bissex/django-blocklist/-/blob/trunk/README.md
Project-URL: Homepage, https://gitlab.com/paul_bissex/django-blocklist
Project-URL: Repository, https://gitlab.com/paul_bissex/django-blocklist/-/tree/trunk
